[{"ID":2001,"Name":"蘋果","AddHP":5,"AddMP":0,"HasBuff":0,"ATK":0,"DEF":0,"MTK":0,"MEF":0,"AGI":0,"SEN":0,"BuffComment":null},
{"ID":2002,"Name":"香菇肉","AddHP":5,"AddMP":0,"HasBuff":0,"ATK":0,"DEF":0,"MTK":0,"MEF":0,"AGI":0,"SEN":0,"BuffComment":null},
{"ID":2003,"Name":"烤香菇串","AddHP":20,"AddMP":20,"HasBuff":0,"ATK":0,"DEF":0,"MTK":0,"MEF":0,"AGI":0,"SEN":0,"BuffComment":null},
{"ID":2004,"Name":"野菜","AddHP":5,"AddMP":0,"HasBuff":0,"ATK":0,"DEF":0,"MTK":0,"MEF":0,"AGI":0,"SEN":0,"BuffComment":null},
{"ID":2005,"Name":"考野菜香菇串","AddHP":30,"AddMP":30,"HasBuff":0,"ATK":0,"DEF":0,"MTK":0,"MEF":0,"AGI":0,"SEN":0,"BuffComment":null},
{"ID":2006,"Name":"獸肉","AddHP":10,"AddMP":0,"HasBuff":0,"ATK":0,"DEF":0,"MTK":0,"MEF":0,"AGI":0,"SEN":0,"BuffComment":null},
{"ID":2007,"Name":"烤肉串","AddHP":30,"AddMP":30,"HasBuff":0,"ATK":0,"DEF":0,"MTK":0,"MEF":0,"AGI":0,"SEN":0,"BuffComment":null},
{"ID":2008,"Name":"香菇烤肉串","AddHP":40,"AddMP":40,"HasBuff":0,"ATK":0,"DEF":0,"MTK":0,"MEF":0,"AGI":0,"SEN":0,"BuffComment":null},
{"ID":2009,"Name":"綜合烤肉串","AddHP":50,"AddMP":50,"HasBuff":0,"ATK":0,"DEF":0,"MTK":0,"MEF":0,"AGI":0,"SEN":0,"BuffComment":null},
{"ID":2010,"Name":"豪華烤肉串","AddHP":60,"AddMP":60,"HasBuff":0,"ATK":0,"DEF":0,"MTK":0,"MEF":0,"AGI":0,"SEN":0,"BuffComment":null},
{"ID":3001,"Name":"小回復藥","AddHP":20,"AddMP":0,"HasBuff":0,"ATK":0,"DEF":0,"MTK":0,"MEF":0,"AGI":0,"SEN":0,"BuffComment":null},
{"ID":3002,"Name":"回復藥","AddHP":40,"AddMP":0,"HasBuff":0,"ATK":0,"DEF":0,"MTK":0,"MEF":0,"AGI":0,"SEN":0,"BuffComment":null},
{"ID":3003,"Name":"大回復藥","AddHP":80,"AddMP":0,"HasBuff":0,"ATK":0,"DEF":0,"MTK":0,"MEF":0,"AGI":0,"SEN":0,"BuffComment":null},
{"ID":3004,"Name":"特大回復藥","AddHP":160,"AddMP":0,"HasBuff":0,"ATK":0,"DEF":0,"MTK":0,"MEF":0,"AGI":0,"SEN":0,"BuffComment":null},
{"ID":3005,"Name":"終極回復藥","AddHP":320,"AddMP":0,"HasBuff":0,"ATK":0,"DEF":0,"MTK":0,"MEF":0,"AGI":0,"SEN":0,"BuffComment":null}]